{
  "theme": {
    "id": "banner-05",
    "defaultStyle": {
      "textColor": "#000000",
      "fontSize": 16
    }
  },
  "variables": {
    "collectionName": "NEW COLLECTION",
    "subtitle": "Winter 2026",
    "discount": "UP TO 50% OFF"
  },
  "root": {
    "type": "container",
    "id": "banner-root",
    "containerType": "box",
    "layout": {
      "width": { "value": 100, "unit": "percent" },
      "aspectRatio": 0.6
    },
    "style": {
      "backgroundColor": "#F5F5F5",
      "borderRadius": 16
    },
    "children": [
      {
        "type": "element",
        "id": "fashion-image",
        "elementType": "image",
        "bindings": {
          "url": "https://cdn.dummyjson.com/products/images/womens-dresses/Black%20Elegant%20Cocktail%20Dress/1.png"
        },
        "layout": {
          "width": { "value": 100, "unit": "percent" },
          "height": { "value": 100, "unit": "percent" },
          "offset": { "x": 0, "y": 0, "unit": "percent" }
        },
        "style": {
          "borderRadius": 16
        }
      },
      {
        "type": "element",
        "id": "gradient-overlay",
        "elementType": "text",
        "bindings": {
          "text": ""
        },
        "layout": {
          "width": { "value": 100, "unit": "percent" },
          "height": { "value": 40, "unit": "percent" },
          "offset": { "x": 0, "y": 60, "unit": "percent" }
        },
        "style": {
          "backgroundColor": "#00000070",
          "borderRadius": 0
        }
      },
      {
        "type": "element",
        "id": "discount-badge",
        "elementType": "text",
        "bindings": {
          "text": "{{discount}}"
        },
        "layout": {
          "width": { "value": 48, "unit": "percent" },
          "height": { "value": 9, "unit": "percent" },
          "offset": { "x": 4, "y": 4, "unit": "percent" }
        },
        "style": {
          "fontSize": 13,
          "fontWeight": "bold",
          "textColor": "#FFFFFF",
          "textAlign": "center",
          "backgroundColor": "#E91E63DD",
          "borderRadius": 18,
          "shadowColor": "#E91E6360",
          "shadowRadius": 6,
          "shadowOffsetX": 0,
          "shadowOffsetY": 3
        }
      },
      {
        "type": "element",
        "id": "collection-label",
        "elementType": "text",
        "bindings": {
          "text": "{{collectionName}}"
        },
        "layout": {
          "width": { "value": 90, "unit": "percent" },
          "offset": { "x": 5, "y": 68, "unit": "percent" }
        },
        "style": {
          "fontSize": 26,
          "fontWeight": "bold",
          "textColor": "#FFFFFF",
          "textAlign": "center",
          "shadowColor": "#00000060",
          "shadowRadius": 4,
          "shadowOffsetX": 0,
          "shadowOffsetY": 2
        }
      },
      {
        "type": "element",
        "id": "subtitle-text",
        "elementType": "text",
        "bindings": {
          "text": "{{subtitle}}"
        },
        "layout": {
          "width": { "value": 90, "unit": "percent" },
          "offset": { "x": 5, "y": 82, "unit": "percent" }
        },
        "style": {
          "fontSize": 16,
          "fontWeight": "medium",
          "textColor": "#FFFFFFDD",
          "textAlign": "center"
        }
      }
    ]
  }
}
